sclock/__init__.py
sclock/clock.py
tests/__init__.py
tests/unit_test.py
sclock-0.1.0.dist-info/LICENSE
sclock-0.1.0.dist-info/METADATA
sclock-0.1.0.dist-info/WHEEL
sclock-0.1.0.dist-info/top_level.txt
sclock-0.1.0.dist-info/RECORD
