Metadata-Version: 2.1
Name: sclock
Version: 0.1.0
Summary: Vanilla python clock implementation for easy measurement of functions and with blocks.
Home-page: https://github.com/TempledUX/sclock
Author: templedux
Author-email: edux98g@gmail.com
Classifier: Programming Language :: Python :: 3
Classifier: License :: OSI Approved :: MIT License
Classifier: Operating System :: OS Independent
Requires-Python: >=3.9
License-File: LICENSE
